accountingkits/__init__.py
accountingkits/_version.py
accountingkits/CrawlerApi/ApiT.py
accountingkits/CrawlerApi/CrawlerT.py
accountingkits/CrawlerApi/WayBackT.py
accountingkits/CrawlerApi/_WebT.py
accountingkits/CrawlerApi/__init__.py
accountingkits/DataPrepare/DataBaseT.py
accountingkits/DataPrepare/FuzzyMatchT.py
accountingkits/DataPrepare/NaDupOutlierT.py
accountingkits/DataPrepare/ReaderT.py
accountingkits/DataPrepare/SliceSelectT.py
accountingkits/DataPrepare/StringT.py
accountingkits/DataPrepare/__init__.py
accountingkits/OSKit/DirectoryT.py
accountingkits/OSKit/__init__.py
accountingkits/_BasicTools/ArrayLikeT.py
accountingkits/_BasicTools/DecoratorT.py
accountingkits/_BasicTools/MatrixLikeT.py
accountingkits/_BasicTools/MultiprocessT.py
accountingkits/_BasicTools/UniversalBasicT.py
accountingkits/_BasicTools/__init__.py
accountingkits/_BasicTools/_numbapack/__init__.py
accountingkits/_BasicTools/_numbapack/funcfactory.py
accountingkits-0.1.3.231114b0.dist-info/LICENSE
accountingkits-0.1.3.231114b0.dist-info/METADATA
accountingkits-0.1.3.231114b0.dist-info/WHEEL
accountingkits-0.1.3.231114b0.dist-info/top_level.txt
accountingkits-0.1.3.231114b0.dist-info/RECORD
