Metadata-Version: 2.1
Name: accountingkits
Version: 0.1.3.231114b0
Summary: The kit-package which made for accounting science research
Home-page: https://github.com/qihangZH/accountingkits
Author: zhang qihang
Author-email: 694499657@qq.com
Classifier: Programming Language :: Python :: 3
Classifier: License :: OSI Approved :: MIT License
Classifier: Operating System :: OS Independent
License-File: LICENSE
